HersheyFonts/HersheyFonts.py
HersheyFonts/__init__.py
HersheyFonts/__main__.py
tests/__init__.py
tests/test_HersheyFonts.py
Hershey_Fonts-2.0.0.dist-info/LICENSE
Hershey_Fonts-2.0.0.dist-info/METADATA
Hershey_Fonts-2.0.0.dist-info/WHEEL
Hershey_Fonts-2.0.0.dist-info/entry_points.txt
Hershey_Fonts-2.0.0.dist-info/top_level.txt
Hershey_Fonts-2.0.0.dist-info/RECORD
