Metadata-Version: 2.1
Name: Hershey-Fonts
Version: 2.0.0
Summary: Vector font package with built-in fonts and font rendering iterators
Home-page: https://github.com/apshu/HersheyFonts
Author: Attila
Author-email: attila.kolinger@gmail.com
License: MIT License
Platform: all
Classifier: Programming Language :: Python :: 3
Classifier: Programming Language :: Python :: 2.7
Classifier: Topic :: Text Processing :: Fonts
Classifier: Topic :: Multimedia :: Graphics
Classifier: Topic :: Scientific/Engineering :: Visualization
Classifier: Topic :: Scientific/Engineering
Classifier: Intended Audience :: Developers
Classifier: Development Status :: 5 - Production/Stable
Classifier: License :: OSI Approved :: MIT License
Classifier: Operating System :: OS Independent
Requires-Python: >=2.7
